inspect_cyber/__init__.py
inspect_cyber/_registry.py
inspect_cyber/dataset/__init__.py
inspect_cyber/dataset/_agentic_eval_dataset.py
inspect_cyber/dataset/_factory.py
inspect_cyber/model/__init__.py
inspect_cyber/model/_model.py
inspect_cyber/py.typed
inspect_cyber/solvers/__init__.py
inspect_cyber/solvers/_verify_solutions.py
inspect_cyber/task/__init__.py
inspect_cyber/task/_task.py
inspect_cyber-0.1.0.dist-info/LICENSE
inspect_cyber-0.1.0.dist-info/METADATA
inspect_cyber-0.1.0.dist-info/WHEEL
inspect_cyber-0.1.0.dist-info/entry_points.txt
inspect_cyber-0.1.0.dist-info/RECORD
