Metadata-Version: 2.3
Name: inspect_cyber
Version: 0.1.0
Summary: An Inspect extension for cyber evaluations
Author: UK AI Security Institute
Requires-Python: >=3.10,<4.0
Classifier: Programming Language :: Python :: 3
Classifier: Programming Language :: Python :: 3.10
Classifier: Programming Language :: Python :: 3.11
Classifier: Programming Language :: Python :: 3.12
Classifier: Programming Language :: Python :: 3.13
Requires-Dist: inspect-ai (>=0.3.86,<0.4.0)
